shed.py
shed_sh-1.0.0.dist-info/DESCRIPTION.rst
shed_sh-1.0.0.dist-info/entry_points.txt
shed_sh-1.0.0.dist-info/METADATA
shed_sh-1.0.0.dist-info/metadata.json
shed_sh-1.0.0.dist-info/RECORD
shed_sh-1.0.0.dist-info/top_level.txt
shed_sh-1.0.0.dist-info/WHEEL
