Metadata-Version: 2.0
Name: shed-sh
Version: 1.0.0
Summary: Don't run "curl | sh" again. Use "curl | shed" to verify scripts before running.
Home-page: https://github.com/mplewis/shed
Author: Matthew Lewis
Author-email: matt@mplewis.com
License: MIT
Platform: UNKNOWN
Classifier: Development Status :: 5 - Production/Stable
Classifier: Natural Language :: English
Classifier: License :: OSI Approved :: MIT License
Classifier: Operating System :: OS Independent
Classifier: Programming Language :: Python
Classifier: Programming Language :: Python :: 3
Classifier: Programming Language :: Python :: 3.4
Classifier: Topic :: Utilities
Classifier: Topic :: System :: Shells
Classifier: Topic :: System :: System Shells
Classifier: Topic :: Text Processing :: Markup
